crypticgen/__init__.py
crypticgen/cli.py
crypticgen/core.py
crypticgen-0.1.0.dist-info/licenses/LICENSE
crypticgen-0.1.0.dist-info/METADATA
crypticgen-0.1.0.dist-info/WHEEL
crypticgen-0.1.0.dist-info/entry_points.txt
crypticgen-0.1.0.dist-info/top_level.txt
crypticgen-0.1.0.dist-info/RECORD
